pyipx800v3_async/__init__.py
pyipx800v3_async/exceptions.py
pyipx800v3_async/pyipx800v3_async.py
pyipx800v3_async-0.4.1.dist-info/METADATA
pyipx800v3_async-0.4.1.dist-info/WHEEL
pyipx800v3_async-0.4.1.dist-info/top_level.txt
pyipx800v3_async-0.4.1.dist-info/RECORD
