Metadata-Version: 2.4
Name: pyipx800v3_async
Version: 0.4.1
Summary: Asynchronous lib to interact with IPX800v3
Author-email: Xavier ROQUES <xavier.roques@gmail.com>
Requires-Dist: aiohttp>=3.9.3
Requires-Dist: async_timeout>=4.0.3
